[{"id":"pe7239","name":"Krusevo","lat":41.3432,"lon":21.2569,"alt":1411,"dirs":["NE","E","SE","SW","W","NW"],"dirsGood":["NE","E","SE","SW","W"],"tags":["xc","thermals","soaring","flatland"],"country":"MK","link":"https://www.paraglidingearth.com/pgearth/index.php?site=7239"},{"id":"pe7240","name":"Ohrid","lat":40.9546,"lon":20.8124,"alt":1578,"dirs":["SW","W","NW"],"dirsGood":["SW","W","NW"],"tags":["xc","thermals","soaring"],"country":"MK","link":"https://www.paraglidingearth.com/pgearth/index.php?site=7240"},{"id":"pe7315","name":"Skopska Crna Gora","lat":42.1686,"lon":21.4761,"alt":1125,"dirs":["S","SW","W"],"dirsGood":["S","SW","W"],"tags":["xc","thermals","soaring"],"country":"MK","link":"https://www.paraglidingearth.com/pgearth/index.php?site=7315"},{"id":"pe7316","name":"Ajvatovci","lat":42.0052,"lon":21.6109,"alt":306,"dirs":["NE","E","SE"],"dirsGood":["NE","E","SE"],"tags":["thermals","soaring"],"country":"MK","link":"https://www.paraglidingearth.com/pgearth/index.php?site=7316"},{"id":"pe7317","name":"Popova Shapka","lat":42.0078,"lon":20.8961,"alt":1598,"dirs":["NE","E","SE"],"dirsGood":["NE","E","SE"],"tags":["xc","thermals","soaring","flatland"],"country":"MK","link":"https://www.paraglidingearth.com/pgearth/index.php?site=7317"},{"id":"pe7318","name":"Ribnik","lat":41.4036,"lon":21.4241,"alt":768,"dirs":["N","NE","E","SE","S","SW","W"],"dirsGood":["N","NE","E","SE","S","SW","W"],"tags":["thermals","soaring"],"country":"MK","link":"https://www.paraglidingearth.com/pgearth/index.php?site=7318"},{"id":"pe7319","name":"Sliva","lat":41.2495,"lon":21.5843,"alt":1193,"dirs":["SW","W"],"dirsGood":["SW","W"],"tags":["xc","thermals","soaring"],"country":"MK","link":"https://www.paraglidingearth.com/pgearth/index.php?site=7319"},{"id":"pe13779","name":"Bukovik","lat":41.7818,"lon":22.9333,"alt":1633,"dirs":[],"dirsGood":[],"tags":[],"country":"MK","link":"https://www.paraglidingearth.com/pgearth/index.php?site=13779"},{"id":"pe15068","name":"Chuka","lat":41.0045,"lon":21.1097,"alt":1825,"dirs":["S","SW","W","NW"],"dirsGood":["SW","W","NW"],"tags":["thermals","soaring"],"country":"MK","link":"https://www.paraglidingearth.com/pgearth/index.php?site=15068"},{"id":"pe19702","name":"Bogoslovec","lat":41.7672,"lon":22.0158,"alt":702,"dirs":["N","NE","S","SW","W","NW"],"dirsGood":["N","NE"],"tags":["thermals","soaring"],"country":"MK","link":"https://www.paraglidingearth.com/pgearth/index.php?site=19702"},{"id":"pe22647","name":"Mavrovo","lat":41.6502,"lon":20.7162,"alt":1709,"dirs":["NE","E"],"dirsGood":["NE"],"tags":[],"country":"MK","link":"https://www.paraglidingearth.com/pgearth/index.php?site=22647"},{"id":"pe22648","name":"Struga","lat":41.1646,"lon":20.586,"alt":1581,"dirs":["NE","E","SE"],"dirsGood":["E"],"tags":["thermals"],"country":"MK","link":"https://www.paraglidingearth.com/pgearth/index.php?site=22648"},{"id":"pe22965","name":"Treskavec","lat":41.3995,"lon":21.5346,"alt":1205,"dirs":[],"dirsGood":[],"tags":[],"country":"MK","link":"https://www.paraglidingearth.com/pgearth/index.php?site=22965"},{"id":"pe23091","name":"Skopje - Vodno","lat":41.9654,"lon":21.3911,"alt":1038,"dirs":["N","NE","NW"],"dirsGood":["N","NW"],"tags":["thermals","soaring"],"country":"MK","link":"https://www.paraglidingearth.com/pgearth/index.php?site=23091"},{"id":"pe23092","name":"Cegrane","lat":41.825,"lon":20.9931,"alt":1017,"dirs":["N","W","NW"],"dirsGood":["NW"],"tags":["xc","thermals","soaring"],"country":"MK","link":"https://www.paraglidingearth.com/pgearth/index.php?site=23092"}]